tidevice/__init__.py
tidevice/__main__.py
tidevice/_ca.py
tidevice/_compat.py
tidevice/_crash.py
tidevice/_device.py
tidevice/_hexdump.py
tidevice/_imagemounter.py
tidevice/_installation.py
tidevice/_instruments.py
tidevice/_ipautil.py
tidevice/_perf.py
tidevice/_proto.py
tidevice/_relay.py
tidevice/_safe_socket.py
tidevice/_sync.py
tidevice/_types.py
tidevice/_usbmux.py
tidevice/_utils.py
tidevice/_version.py
tidevice/_wdaproxy.py
tidevice/bplist.py
tidevice/datatypes.py
tidevice/exceptions.py
tidevice/plistlib2.py
tidevice/requests_usbmux.py
tidevice/session.py
tidevice/struct2.py
tidevice-0.12.10.dist-info/AUTHORS
tidevice-0.12.10.dist-info/LICENSE
tidevice-0.12.10.dist-info/METADATA
tidevice-0.12.10.dist-info/WHEEL
tidevice-0.12.10.dist-info/entry_points.txt
tidevice-0.12.10.dist-info/pbr.json
tidevice-0.12.10.dist-info/top_level.txt
tidevice-0.12.10.dist-info/RECORD
