Metadata-Version: 2.1
Name: tidevice
Version: 0.12.10
Summary: UNKNOWN
Home-page: https://github.com/alibaba/tidevice
Author: 圣翔
Author-email: codeskyblue@gmail.com
License: MIT
Platform: UNKNOWN
Classifier: Development Status :: 4 - Beta
Classifier: Environment :: Console
Classifier: Intended Audience :: Developers
Classifier: Operating System :: POSIX
Classifier: Programming Language :: Python :: 3
Classifier: Topic :: Software Development :: Libraries :: Python Modules
Classifier: Topic :: Software Development :: Testing
Requires-Python: >=3.6
Requires-Dist: Pillow
Requires-Dist: requests
Requires-Dist: colored
Requires-Dist: packaging
Requires-Dist: tornado
Requires-Dist: simple-tornado >=0.2.2
Requires-Dist: retry
Requires-Dist: simplejson
Requires-Dist: tabulate
Requires-Dist: logzero
Requires-Dist: deprecation
Provides-Extra: openssl
Requires-Dist: pyOpenSSL ; extra == 'openssl'
Requires-Dist: pyasn1 ; extra == 'openssl'
